CHANGELOG.txt
LICENCE.txt
MANIFEST.in
README.txt
how_to_submit_to_pypi.txt
setup.py
elutils/__init__.py
elutils/decorators.py
elutils/log.py
elutils/osio.py
elutils/performance.py
elutils/testing.py
elutils/utils.py
elutils.egg-info/PKG-INFO
elutils.egg-info/SOURCES.txt
elutils.egg-info/dependency_links.txt
elutils.egg-info/top_level.txt
tests/runner.py
tests/test_decorators.py
tests/test_osio.py
tests/test_utils.py
venv/bin/activate_this.py
venv/lib/python2.7/UserDict.py
venv/lib/python2.7/_abcoll.py
venv/lib/python2.7/_weakrefset.py
venv/lib/python2.7/abc.py
venv/lib/python2.7/codecs.py
venv/lib/python2.7/copy_reg.py
venv/lib/python2.7/fnmatch.py
venv/lib/python2.7/genericpath.py
venv/lib/python2.7/linecache.py
venv/lib/python2.7/locale.py
venv/lib/python2.7/no-global-site-packages.txt
venv/lib/python2.7/ntpath.py
venv/lib/python2.7/orig-prefix.txt
venv/lib/python2.7/os.py
venv/lib/python2.7/posixpath.py
venv/lib/python2.7/re.py
venv/lib/python2.7/site.py
venv/lib/python2.7/sre.py
venv/lib/python2.7/sre_compile.py
venv/lib/python2.7/sre_constants.py
venv/lib/python2.7/sre_parse.py
venv/lib/python2.7/stat.py
venv/lib/python2.7/types.py
venv/lib/python2.7/warnings.py
venv/lib/python2.7/distutils/__init__.py
venv/lib/python2.7/encodings/__init__.py
venv/lib/python2.7/encodings/aliases.py
venv/lib/python2.7/encodings/ascii.py
venv/lib/python2.7/encodings/base64_codec.py
venv/lib/python2.7/encodings/big5.py
venv/lib/python2.7/encodings/big5hkscs.py
venv/lib/python2.7/encodings/bz2_codec.py
venv/lib/python2.7/encodings/charmap.py
venv/lib/python2.7/encodings/cp037.py
venv/lib/python2.7/encodings/cp1006.py
venv/lib/python2.7/encodings/cp1026.py
venv/lib/python2.7/encodings/cp1140.py
venv/lib/python2.7/encodings/cp1250.py
venv/lib/python2.7/encodings/cp1251.py
venv/lib/python2.7/encodings/cp1252.py
venv/lib/python2.7/encodings/cp1253.py
venv/lib/python2.7/encodings/cp1254.py
venv/lib/python2.7/encodings/cp1255.py
venv/lib/python2.7/encodings/cp1256.py
venv/lib/python2.7/encodings/cp1257.py
venv/lib/python2.7/encodings/cp1258.py
venv/lib/python2.7/encodings/cp424.py
venv/lib/python2.7/site-packages/pip-20.2.3.dist-info/LICENSE.txt
venv/lib/python2.7/site-packages/pip-20.2.3.dist-info/entry_points.txt
venv/lib/python2.7/site-packages/pip-20.2.3.dist-info/top_level.txt
venv/lib/python2.7/site-packages/setuptools-44.1.1.dist-info/dependency_links.txt
venv/lib/python2.7/site-packages/setuptools-44.1.1.dist-info/entry_points.txt
venv/lib/python2.7/site-packages/setuptools-44.1.1.dist-info/top_level.txt
venv/lib/python2.7/site-packages/wheel-0.35.1.dist-info/LICENSE.txt
venv/lib/python2.7/site-packages/wheel-0.35.1.dist-info/entry_points.txt
venv/lib/python2.7/site-packages/wheel-0.35.1.dist-info/top_level.txt
venv/local/lib/python2.7/site-packages/pip-20.2.3.dist-info/LICENSE.txt
venv/local/lib/python2.7/site-packages/pip-20.2.3.dist-info/entry_points.txt
venv/local/lib/python2.7/site-packages/pip-20.2.3.dist-info/top_level.txt
venv/local/lib/python2.7/site-packages/setuptools-44.1.1.dist-info/dependency_links.txt
venv/local/lib/python2.7/site-packages/setuptools-44.1.1.dist-info/entry_points.txt
venv/local/lib/python2.7/site-packages/setuptools-44.1.1.dist-info/top_level.txt
venv/local/lib/python2.7/site-packages/wheel-0.35.1.dist-info/LICENSE.txt
venv/local/lib/python2.7/site-packages/wheel-0.35.1.dist-info/entry_points.txt
venv/local/lib/python2.7/site-packages/wheel-0.35.1.dist-info/top_level.txt
