Metadata-Version: 1.1
Name: elutils
Version: 0.0.11
Summary: A small package of my utilities
Home-page: UNKNOWN
Author: Emil Elgaard
Author-email: shivan@shivan.dk
License: MIT
Keywords: utilities
Platform: UNKNOWN
Classifier: Development Status :: 3 - Alpha
Classifier: Intended Audience :: Education
Classifier: Operating System :: OS Independent
Classifier: License :: OSI Approved :: MIT License
Classifier: Programming Language :: Python :: 3
